{
  "meta": {
    "egoId": 204480,
    "egoName": "Rogério Correia",
    "generatedAt": "2026-06-05T14:55:30.629662Z",
    "sources": [
      "camara",
      "tse"
    ],
    "summary": null,
    "disclaimer": "Dados públicos. Conexões não são acusações de irregularidade."
  },
  "nodes": [
    {
      "id": 204480,
      "name": "Rogério Correia",
      "category": "politician",
      "connectionCount": 15
    },
    {
      "id": 7,
      "name": "#NULO",
      "category": "donor",
      "connectionCount": 1
    },
    {
      "id": 14,
      "name": "ADRIANE MARIA ARANTES DE CARVALHO",
      "category": "donor",
      "connectionCount": 1
    },
    {
      "id": 8,
      "name": "ELEICAO 2022 MARCOS JOSERALDO LEMOS DEPUTADO ESTADUAL",
      "category": "donor",
      "connectionCount": 1
    },
    {
      "id": 13,
      "name": "FLAVIA CALDEIRA MELLO",
      "category": "donor",
      "connectionCount": 1
    },
    {
      "id": 9,
      "name": "GETULIO DA CRUZ TEIXEIRA",
      "category": "donor",
      "connectionCount": 1
    },
    {
      "id": 10,
      "name": "GLAUCIA DE FATIMA BATISTA",
      "category": "donor",
      "connectionCount": 1
    },
    {
      "id": 15,
      "name": "LUCAS MONTEIRO COSTA DIAS",
      "category": "donor",
      "connectionCount": 1
    },
    {
      "id": 11,
      "name": "LUIS CARLOS DA SILVA",
      "category": "donor",
      "connectionCount": 1
    },
    {
      "id": 3,
      "name": "LUIS GUSTAVO D AVILA RIANI",
      "category": "donor",
      "connectionCount": 1
    },
    {
      "id": 6,
      "name": "MAXIMILIANO NAGL GARCEZ",
      "category": "donor",
      "connectionCount": 1
    },
    {
      "id": 1,
      "name": "PARTIDO DOS TRABALHADORES - BRASIL - BR - NACIONAL",
      "category": "donor",
      "connectionCount": 1
    },
    {
      "id": 2,
      "name": "PARTIDO DOS TRABALHADORES PT",
      "category": "donor",
      "connectionCount": 1
    },
    {
      "id": 5,
      "name": "PEDRO DE FREITAS MOREIRA",
      "category": "donor",
      "connectionCount": 1
    },
    {
      "id": 4,
      "name": "RINOBOX SOLUCOES FINANCEIRAS LTDA",
      "category": "donor",
      "connectionCount": 1
    },
    {
      "id": 12,
      "name": "VINICIUS FAVILLA FUZETI",
      "category": "donor",
      "connectionCount": 1
    }
  ],
  "links": [
    {
      "id": 1,
      "source": 1,
      "target": 204480,
      "connectionType": "doacao",
      "description": "Doação de campanha de R$1.800.000,00 em 2022 registrada no TSE (3 receitas, 19/08/2022–16/09/2022)",
      "strength": 1
    },
    {
      "id": 2,
      "source": 2,
      "target": 204480,
      "connectionType": "doacao",
      "description": "Doação de campanha de R$62.500,00 em 2022 registrada no TSE (29/09/2022)",
      "strength": 1
    },
    {
      "id": 3,
      "source": 3,
      "target": 204480,
      "connectionType": "doacao",
      "description": "Doação de campanha de R$20.000,00 em 2022 registrada no TSE (16/08/2022)",
      "strength": 1
    },
    {
      "id": 4,
      "source": 4,
      "target": 204480,
      "connectionType": "doacao",
      "description": "Doação de campanha de R$7.496,00 em 2022 registrada no TSE (2 receitas, 26/08/2022–07/10/2022)",
      "strength": 1
    },
    {
      "id": 5,
      "source": 5,
      "target": 204480,
      "connectionType": "doacao",
      "description": "Doação de campanha de R$5.000,00 em 2022 registrada no TSE (29/09/2022)",
      "strength": 1
    },
    {
      "id": 6,
      "source": 6,
      "target": 204480,
      "connectionType": "doacao",
      "description": "Doação de campanha de R$3.000,00 em 2022 registrada no TSE (30/09/2022)",
      "strength": 1
    },
    {
      "id": 7,
      "source": 7,
      "target": 204480,
      "connectionType": "doacao",
      "description": "Doação de campanha de R$2.535,46 em 2022 registrada no TSE (2 receitas, 30/08/2022–30/09/2022)",
      "strength": 1
    },
    {
      "id": 8,
      "source": 8,
      "target": 204480,
      "connectionType": "doacao",
      "description": "Doação de campanha de R$1.280,00 em 2022 registrada no TSE (3 receitas, 24/08/2022–23/09/2022)",
      "strength": 1
    },
    {
      "id": 9,
      "source": 9,
      "target": 204480,
      "connectionType": "doacao",
      "description": "Doação de campanha de R$1.000,00 em 2022 registrada no TSE (19/09/2022)",
      "strength": 1
    },
    {
      "id": 10,
      "source": 10,
      "target": 204480,
      "connectionType": "doacao",
      "description": "Doação de campanha de R$1.000,00 em 2022 registrada no TSE (20/09/2022)",
      "strength": 1
    },
    {
      "id": 11,
      "source": 11,
      "target": 204480,
      "connectionType": "doacao",
      "description": "Doação de campanha de R$1.000,00 em 2022 registrada no TSE (01/09/2022)",
      "strength": 1
    },
    {
      "id": 12,
      "source": 12,
      "target": 204480,
      "connectionType": "doacao",
      "description": "Doação de campanha de R$1.000,00 em 2022 registrada no TSE (16/08/2022)",
      "strength": 1
    },
    {
      "id": 13,
      "source": 13,
      "target": 204480,
      "connectionType": "doacao",
      "description": "Doação de campanha de R$700,00 em 2022 registrada no TSE (20/09/2022)",
      "strength": 1
    },
    {
      "id": 14,
      "source": 14,
      "target": 204480,
      "connectionType": "doacao",
      "description": "Doação de campanha de R$500,00 em 2022 registrada no TSE (08/09/2022)",
      "strength": 1
    },
    {
      "id": 15,
      "source": 15,
      "target": 204480,
      "connectionType": "doacao",
      "description": "Doação de campanha de R$100,00 em 2022 registrada no TSE (11/10/2022)",
      "strength": 1
    }
  ]
}