{
  "meta": {
    "egoId": 204456,
    "egoName": "Gutemberg Reis",
    "generatedAt": "2026-06-05T14:55:27.674774Z",
    "sources": [
      "camara",
      "receita",
      "tse"
    ],
    "summary": null,
    "disclaimer": "Dados públicos. Conexões não são acusações de irregularidade."
  },
  "nodes": [
    {
      "id": 204456,
      "name": "Gutemberg Reis",
      "category": "politician",
      "connectionCount": 21
    },
    {
      "id": 11,
      "name": "ATHOS 2013 LOCACOES E EQUIPAMENTOS LTDA",
      "category": "company",
      "connectionCount": 1
    },
    {
      "id": 12,
      "name": "AUTO SERVICOS BR JERUSALEM LTDA",
      "category": "company",
      "connectionCount": 1
    },
    {
      "id": 5,
      "name": "CARLOS EDUARDO MERENLENDER",
      "category": "donor",
      "connectionCount": 1
    },
    {
      "id": 8,
      "name": "CELMA MOTA CORREA",
      "category": "donor",
      "connectionCount": 1
    },
    {
      "id": 13,
      "name": "CONSPLAN CONSTRUCOES E PARTICIPACOES LTDA",
      "category": "company",
      "connectionCount": 1
    },
    {
      "id": 7,
      "name": "ERNESTO LUIZ OTERO NETO",
      "category": "donor",
      "connectionCount": 1
    },
    {
      "id": 14,
      "name": "G9 PARTICIPACOES E EMPREENDIMENTOS IMOBILIARIOS LTDA",
      "category": "company",
      "connectionCount": 1
    },
    {
      "id": 15,
      "name": "GO9 IMPORTACAO E EXPORTACAO LTDA",
      "category": "company",
      "connectionCount": 1
    },
    {
      "id": 16,
      "name": "GR CAXIAS CONSTRUCOES E EMPREENDIMENTOS IMOBILIARIOS LTDA",
      "category": "company",
      "connectionCount": 1
    },
    {
      "id": 17,
      "name": "GW CORRETORA DE IMOVEIS LTDA",
      "category": "company",
      "connectionCount": 1
    },
    {
      "id": 18,
      "name": "HODAR DISTRIBUIDORA DE PNEUS E BATERIAS LTDA",
      "category": "company",
      "connectionCount": 1
    },
    {
      "id": 19,
      "name": "HORTO OFICINA DA TERRA COMERCIO DE PLANTAS LTDA",
      "category": "company",
      "connectionCount": 1
    },
    {
      "id": 2,
      "name": "JONATHAS REGO MONTEIRO PORTO NETO",
      "category": "donor",
      "connectionCount": 1
    },
    {
      "id": 9,
      "name": "JOSE SERGIO DA SILVA TAVARES",
      "category": "donor",
      "connectionCount": 1
    },
    {
      "id": 4,
      "name": "LUIZ FERNANDO DE OLIVEIRA CALIXTO",
      "category": "donor",
      "connectionCount": 1
    },
    {
      "id": 10,
      "name": "MARCELO CORREIA BARROS",
      "category": "donor",
      "connectionCount": 1
    },
    {
      "id": 3,
      "name": "MARCUS VINICIUS DE OLIVEIRA CALIXTO",
      "category": "donor",
      "connectionCount": 1
    },
    {
      "id": 20,
      "name": "MINERADORA BRITAR LTDA",
      "category": "company",
      "connectionCount": 1
    },
    {
      "id": 1,
      "name": "MOVIMENTO DEMOCRATICO BRASILEIRO - BRASIL - BR - NACIONAL",
      "category": "donor",
      "connectionCount": 1
    },
    {
      "id": 6,
      "name": "SERGIO LUIS DE OLIVEIRA GUEDES",
      "category": "donor",
      "connectionCount": 1
    },
    {
      "id": 21,
      "name": "WCP SOLUCOES LOGISTICAS LTDA",
      "category": "company",
      "connectionCount": 1
    }
  ],
  "links": [
    {
      "id": 1,
      "source": 1,
      "target": 204456,
      "connectionType": "doacao",
      "description": "Doação de campanha de R$2.700.000,00 em 2022 registrada no TSE (2 receitas, 23/08/2022–21/09/2022)",
      "strength": 1
    },
    {
      "id": 2,
      "source": 2,
      "target": 204456,
      "connectionType": "doacao",
      "description": "Doação de campanha de R$64.300,00 em 2022 registrada no TSE (2 receitas, 30/09/2022–25/10/2022)",
      "strength": 1
    },
    {
      "id": 3,
      "source": 3,
      "target": 204456,
      "connectionType": "doacao",
      "description": "Doação de campanha de R$41.000,00 em 2022 registrada no TSE (2 receitas, 29/09/2022–19/10/2022)",
      "strength": 1
    },
    {
      "id": 4,
      "source": 4,
      "target": 204456,
      "connectionType": "doacao",
      "description": "Doação de campanha de R$24.000,00 em 2022 registrada no TSE (2 receitas, 19/09/2022–29/09/2022)",
      "strength": 1
    },
    {
      "id": 5,
      "source": 5,
      "target": 204456,
      "connectionType": "doacao",
      "description": "Doação de campanha de R$20.000,00 em 2022 registrada no TSE (30/09/2022)",
      "strength": 1
    },
    {
      "id": 6,
      "source": 6,
      "target": 204456,
      "connectionType": "doacao",
      "description": "Doação de campanha de R$20.000,00 em 2022 registrada no TSE (29/09/2022)",
      "strength": 1
    },
    {
      "id": 7,
      "source": 7,
      "target": 204456,
      "connectionType": "doacao",
      "description": "Doação de campanha de R$10.040,00 em 2022 registrada no TSE (30/09/2022)",
      "strength": 1
    },
    {
      "id": 8,
      "source": 8,
      "target": 204456,
      "connectionType": "doacao",
      "description": "Doação de campanha de R$10.000,00 em 2022 registrada no TSE (30/09/2022)",
      "strength": 1
    },
    {
      "id": 9,
      "source": 9,
      "target": 204456,
      "connectionType": "doacao",
      "description": "Doação de campanha de R$4.000,00 em 2022 registrada no TSE (26/08/2022)",
      "strength": 1
    },
    {
      "id": 10,
      "source": 10,
      "target": 204456,
      "connectionType": "doacao",
      "description": "Doação de campanha de R$3.000,00 em 2022 registrada no TSE (26/08/2022)",
      "strength": 1
    },
    {
      "id": 11,
      "source": 204456,
      "target": 11,
      "connectionType": "socio",
      "description": "Participação societária registrada na base CNPJ/Receita Federal (qualificação 49), entrada em 20130815",
      "strength": 1
    },
    {
      "id": 12,
      "source": 204456,
      "target": 12,
      "connectionType": "socio",
      "description": "Participação societária registrada na base CNPJ/Receita Federal (qualificação 22), entrada em 20001218",
      "strength": 1
    },
    {
      "id": 13,
      "source": 204456,
      "target": 13,
      "connectionType": "socio",
      "description": "Participação societária registrada na base CNPJ/Receita Federal (qualificação 49), entrada em 20170712",
      "strength": 1
    },
    {
      "id": 14,
      "source": 204456,
      "target": 14,
      "connectionType": "socio",
      "description": "Participação societária registrada na base CNPJ/Receita Federal (qualificação 49), entrada em 20170620",
      "strength": 1
    },
    {
      "id": 15,
      "source": 204456,
      "target": 15,
      "connectionType": "socio",
      "description": "Participação societária registrada na base CNPJ/Receita Federal (qualificação 22), entrada em 20151222",
      "strength": 1
    },
    {
      "id": 16,
      "source": 204456,
      "target": 16,
      "connectionType": "socio",
      "description": "Participação societária registrada na base CNPJ/Receita Federal (qualificação 49), entrada em 20081210",
      "strength": 1
    },
    {
      "id": 17,
      "source": 204456,
      "target": 17,
      "connectionType": "socio",
      "description": "Participação societária registrada na base CNPJ/Receita Federal (qualificação 49), entrada em 20140124",
      "strength": 1
    },
    {
      "id": 18,
      "source": 204456,
      "target": 18,
      "connectionType": "socio",
      "description": "Participação societária registrada na base CNPJ/Receita Federal (qualificação 05), entrada em 20140103",
      "strength": 1
    },
    {
      "id": 19,
      "source": 204456,
      "target": 19,
      "connectionType": "socio",
      "description": "Participação societária registrada na base CNPJ/Receita Federal (qualificação 49), entrada em 20150924",
      "strength": 1
    },
    {
      "id": 20,
      "source": 204456,
      "target": 20,
      "connectionType": "socio",
      "description": "Participação societária registrada na base CNPJ/Receita Federal (qualificação 05), entrada em 20160506",
      "strength": 1
    },
    {
      "id": 21,
      "source": 204456,
      "target": 21,
      "connectionType": "socio",
      "description": "Participação societária registrada na base CNPJ/Receita Federal (qualificação 49), entrada em 20120110",
      "strength": 1
    }
  ]
}