{
  "meta": {
    "egoId": 220586,
    "egoName": "Rafael Brito",
    "generatedAt": "2026-06-05T18:45:21.695877Z",
    "sources": [
      "camara",
      "receita",
      "tse"
    ],
    "summary": null,
    "disclaimer": "Dados públicos. Conexões não são acusações de irregularidade."
  },
  "nodes": [
    {
      "id": 220586,
      "name": "Rafael Brito",
      "category": "politician",
      "connectionCount": 11
    },
    {
      "id": 10,
      "name": "ALAGOAS ATIVOS S/A",
      "category": "company",
      "connectionCount": 1
    },
    {
      "id": 4,
      "name": "BERNARDO MALTA DE AMORIM",
      "category": "donor",
      "connectionCount": 1
    },
    {
      "id": 5,
      "name": "CARLOS ANTONIO NOGUEIRA GATTO",
      "category": "donor",
      "connectionCount": 1
    },
    {
      "id": 2,
      "name": "ELEICAO 2022 JOSE RENAN VASCONCELOS CALHEIROS FILHO SENADOR",
      "category": "donor",
      "connectionCount": 1
    },
    {
      "id": 6,
      "name": "FLAVIO LUCIO UCHOA DORIA",
      "category": "donor",
      "connectionCount": 1
    },
    {
      "id": 3,
      "name": "FRANCISCO EDLARDO BASTOS DE BRITO",
      "category": "donor",
      "connectionCount": 1
    },
    {
      "id": 9,
      "name": "LIVIA RUSSO DUARTE CAMERINO",
      "category": "donor",
      "connectionCount": 1
    },
    {
      "id": 7,
      "name": "MARCIO AUGUSTO GOMES COELHO",
      "category": "donor",
      "connectionCount": 1
    },
    {
      "id": 1,
      "name": "MOVIMENTO DEMOCRATICO BRASILEIRO - ALAGOAS - AL - ESTADUAL",
      "category": "donor",
      "connectionCount": 1
    },
    {
      "id": 8,
      "name": "RAFAEL DE GOES BRITO",
      "category": "donor",
      "connectionCount": 1
    },
    {
      "id": 11,
      "name": "SUPER SORTE SERVICOS LOTERICOS LTDA",
      "category": "company",
      "connectionCount": 1
    }
  ],
  "links": [
    {
      "id": 1,
      "source": 1,
      "target": 220586,
      "connectionType": "doacao",
      "description": "Doação de campanha de R$400.000,00 em 2022 registrada no TSE (31/08/2022)",
      "strength": 1
    },
    {
      "id": 2,
      "source": 2,
      "target": 220586,
      "connectionType": "doacao",
      "description": "Doação de campanha de R$300.000,00 em 2022 registrada no TSE (14/09/2022)",
      "strength": 1
    },
    {
      "id": 3,
      "source": 3,
      "target": 220586,
      "connectionType": "doacao",
      "description": "Doação de campanha de R$30.000,00 em 2022 registrada no TSE (23/08/2022)",
      "strength": 1
    },
    {
      "id": 4,
      "source": 4,
      "target": 220586,
      "connectionType": "doacao",
      "description": "Doação de campanha de R$25.000,00 em 2022 registrada no TSE (14/09/2022)",
      "strength": 1
    },
    {
      "id": 5,
      "source": 5,
      "target": 220586,
      "connectionType": "doacao",
      "description": "Doação de campanha de R$20.000,00 em 2022 registrada no TSE (14/09/2022)",
      "strength": 1
    },
    {
      "id": 6,
      "source": 6,
      "target": 220586,
      "connectionType": "doacao",
      "description": "Doação de campanha de R$20.000,00 em 2022 registrada no TSE (2 receitas, 16/08/2022–23/08/2022)",
      "strength": 1
    },
    {
      "id": 7,
      "source": 7,
      "target": 220586,
      "connectionType": "doacao",
      "description": "Doação de campanha de R$20.000,00 em 2022 registrada no TSE (13/09/2022)",
      "strength": 1
    },
    {
      "id": 8,
      "source": 8,
      "target": 220586,
      "connectionType": "doacao",
      "description": "Doação de campanha de R$12.385,00 em 2022 registrada no TSE (13/10/2022)",
      "strength": 1
    },
    {
      "id": 9,
      "source": 9,
      "target": 220586,
      "connectionType": "doacao",
      "description": "Doação de campanha de R$5.000,00 em 2022 registrada no TSE (16/08/2022)",
      "strength": 1
    },
    {
      "id": 10,
      "source": 220586,
      "target": 10,
      "connectionType": "socio",
      "description": "Participação societária registrada na base CNPJ/Receita Federal (conselheiro de administração), desde 27/10/2017",
      "strength": 1
    },
    {
      "id": 11,
      "source": 220586,
      "target": 11,
      "connectionType": "socio",
      "description": "Participação societária registrada na base CNPJ/Receita Federal (sócio), desde 01/04/2015",
      "strength": 1
    }
  ]
}