{
  "meta": {
    "egoId": 901186,
    "egoName": "Luis Carlos Heinze",
    "chamber": "senado",
    "photo": "https://www.senado.leg.br/senadores/img/fotos-oficiais/senador1186.jpg",
    "generatedAt": "2026-07-17T04:22:58.003091Z",
    "sources": [
      "cgu_emendas",
      "senado"
    ],
    "sourceCoverage": {
      "cgu_emendas": "emendas individuais de 2023 em diante; coleta local em 25/06/2026",
      "senado": "parlamentares em exercício na consulta; coleta local em 06/06/2026"
    },
    "summary": "Entre 2023 e os registros mais recentes, registram-se R$ 196,2 milhões em emendas empenhadas e R$ 187,8 milhões pagos em nove áreas, principalmente Saúde.",
    "disclaimer": "Dados públicos. Conexões não são acusações de irregularidade."
  },
  "nodes": [
    {
      "id": 901186,
      "name": "Luis Carlos Heinze",
      "category": "politician",
      "connectionCount": 9
    },
    {
      "id": 8,
      "name": "Agricultura",
      "category": "destino",
      "connectionCount": 1
    },
    {
      "id": 7,
      "name": "Ciência e Tecnologia",
      "category": "destino",
      "connectionCount": 1
    },
    {
      "id": 3,
      "name": "Defesa nacional",
      "category": "destino",
      "connectionCount": 1
    },
    {
      "id": 4,
      "name": "Educação",
      "category": "destino",
      "connectionCount": 1
    },
    {
      "id": 2,
      "name": "Encargos especiais",
      "category": "destino",
      "connectionCount": 1
    },
    {
      "id": 9,
      "name": "Relações exteriores",
      "category": "destino",
      "connectionCount": 1
    },
    {
      "id": 1,
      "name": "Saúde",
      "category": "destino",
      "connectionCount": 1
    },
    {
      "id": 5,
      "name": "Segurança pública",
      "category": "destino",
      "connectionCount": 1
    },
    {
      "id": 6,
      "name": "Transporte",
      "category": "destino",
      "connectionCount": 1
    }
  ],
  "links": [
    {
      "id": 1,
      "source": 901186,
      "target": 1,
      "connectionType": "emenda",
      "description": "Emendas individuais destinadas a Saúde: R$97.655.189,00 empenhado, R$92.695.676,00 pago (6 emendas; 2023–2025)",
      "strength": 1
    },
    {
      "id": 2,
      "source": 901186,
      "target": 2,
      "connectionType": "emenda",
      "description": "Emendas individuais destinadas a Encargos especiais: R$93.614.276,00 empenhado, R$93.288.454,00 pago (4 emendas; 2023–2025)",
      "strength": 1
    },
    {
      "id": 3,
      "source": 901186,
      "target": 3,
      "connectionType": "emenda",
      "description": "Emendas individuais destinadas a Defesa nacional: R$1.623.910,00 empenhado, R$904.603,00 pago (3 emendas; 2024–2025)",
      "strength": 1
    },
    {
      "id": 4,
      "source": 901186,
      "target": 4,
      "connectionType": "emenda",
      "description": "Emendas individuais destinadas a Educação: R$969.030,00 empenhado, R$68.729,00 pago (2 emendas; 2024)",
      "strength": 1
    },
    {
      "id": 5,
      "source": 901186,
      "target": 5,
      "connectionType": "emenda",
      "description": "Emendas individuais destinadas a Segurança pública: R$707.200,00 empenhado, R$22.749,00 pago (1 emenda; 2025)",
      "strength": 1
    },
    {
      "id": 6,
      "source": 901186,
      "target": 6,
      "connectionType": "emenda",
      "description": "Emendas individuais destinadas a Transporte: R$600.000,00 empenhado, R$548.023,00 pago (3 emendas; 2023–2025)",
      "strength": 1
    },
    {
      "id": 7,
      "source": 901186,
      "target": 7,
      "connectionType": "emenda",
      "description": "Emendas individuais destinadas a Ciência e Tecnologia: R$500.000,00 empenhado (1 emenda; 2024)",
      "strength": 1
    },
    {
      "id": 8,
      "source": 901186,
      "target": 8,
      "connectionType": "emenda",
      "description": "Emendas individuais destinadas a Agricultura: R$300.000,00 empenhado, R$150.000,00 pago (2 emendas; 2023)",
      "strength": 1
    },
    {
      "id": 9,
      "source": 901186,
      "target": 9,
      "connectionType": "emenda",
      "description": "Emendas individuais destinadas a Relações exteriores: R$207.947,00 empenhado, R$138.582,00 pago (1 emenda; 2024)",
      "strength": 1
    }
  ]
}